colorsphere/__init__.py
colorsphere/__main__.py
colorsphere/colorsphere.py
colorsphere/colorwidgets.py
colorsphere/launcher.py
colorsphere/windowmgr.py
colorsphere-0.1.2.dist-info/LICENSE
colorsphere-0.1.2.dist-info/METADATA
colorsphere-0.1.2.dist-info/WHEEL
colorsphere-0.1.2.dist-info/top_level.txt
colorsphere-0.1.2.dist-info/RECORD
