Metadata-Version: 2.1
Name: colorsphere
Version: 0.1.2
Summary: Select colors on a 3D sphere
Home-page: https://github.com/Anders-Holst/colorsphere
Author: Anders Holst
Author-email: anders.holst@ri.se
License: MIT
Keywords: graphics
Classifier: Development Status :: 4 - Beta
Classifier: Programming Language :: Python :: 2.7
Classifier: Programming Language :: Python :: 3.6
Classifier: Programming Language :: Python :: 3.7
Classifier: Programming Language :: Python :: 3.8
Classifier: Programming Language :: Python :: 3.9
Classifier: Programming Language :: Python :: 3.10
Classifier: Intended Audience :: Developers
Classifier: License :: OSI Approved :: MIT License
Classifier: Topic :: Software Development :: Libraries
Classifier: Topic :: Utilities
License-File: LICENSE
Requires-Dist: matplotlib
Requires-Dist: numpy
